Metadata-Version: 1.1
Name: pynotify1
Version: 0.1.0
Summary: convenient email notification, timing and logging of code execution
Home-page: https://github.com/tom1919
Author: Tom1919
Author-email: py.notify1@gmail.com
License: Apache 2.0
Download-URL: https://github.com/tom1919/PyNotify/archive/refs/tags/v0.1.0.tar.gz
Keywords: email,logging,timimg,notification
Platform: UNKNOWN
Classifier: Development Status :: 3 - Alpha
Classifier: Intended Audience :: Developers
Classifier: Topic :: Software Development :: Build Tools
Classifier: License :: OSI Approved :: MIT License
Classifier: Programming Language :: Python :: 3
Classifier: Programming Language :: Python :: 3.4
Classifier: Programming Language :: Python :: 3.5
Classifier: Programming Language :: Python :: 3.6
